{"ingredients": [
  {
    "itemName": "wheat",
    "foodValue": 10
  },
  {
    "itemName": "cacti",
    "foodValue": 10
  },
  {
    "itemName": "cocoa",
    "foodValue": 10
  },
  {
    "itemName": "crystalplant",
    "price": 5,
    "foodValue": 10
  },
  {
    "itemName": "kelp",
    "price": 5,
    "foodValue": 10
  },
  {
    "itemName": "rice",
    "foodValue": 10
  },
  {
    "itemName": "shroom",
    "foodValue": 10
  },
  {
    "itemName": "portobellomushroomMFM",
    "foodValue": 10
  },
  {
    "itemName": "sugar",
    "foodValue": 10
  },
  {
    "itemName": "clay",
    "price": 4
  },
  {
    "itemName": "giantflowerpetal",
    "price": 5,
    "foodValue": 10
  },
  {
    "itemName": "paper",
    "price": 3
  },
  {
    "itemName": "plantfibre",
    "price": 5,
    "foodValue": 10
  },
  {
    "itemName": "petalblue",
    "price": 5,
    "foodValue": 10
  },
  {
    "itemName": "petalred",
    "price": 5,
    "foodValue": 10
  },
  {
    "itemName": "petalyellow",
    "price": 5,
    "foodValue": 10
  },
  {
    "itemName": "darkwoodmaterial",
    "price": 2
  },
  {
    "itemName": "cobblestonematerial",
    "price": 2
  },
  {
    "itemName": "sand",
    "price": 2
  },
  {
    "itemName": "ice",
    "price": 10
  },
  {
    "itemName": "fleshstrand",
    "price": 5,
    "foodValue": 10
  },
  {
    "itemName": "endomorphicjelly",
    "foodValue": 10
  },
  {
    "itemName": "sugarcaneBMB",
    "foodValue": 5.7
  },
  {
    "itemName": "glass",
    "price": 3
  },
  {
    "name": "liquidmilk",
    "price": 10,
    "foodValue": 10
  }
 ]}